pydataio/__init__.py
pydataio/config_handler.py
pydataio/job_config.py
pydataio/pipeline.py
pydataio/pipeline_config.py
pydataio/schema_registry.py
pydataio/transformer.py
pydataio/config/logging.ini
pydataio/io/__init__.py
pydataio/io/abstract_io.py
pydataio/io/pipes/__init__.py
pydataio/io/pipes/spark/__init__.py
pydataio/io/pipes/spark/batch/__init__.py
pydataio/io/pipes/spark/batch/inputs.py
pydataio/io/pipes/spark/batch/outputs.py
pydataio/io/pipes/spark/streaming/__init__.py
pydataio/io/pipes/spark/streaming/inputs.py
pydataio/io/pipes/spark/streaming/outputs.py
pydataio/io/utils/__init__.py
pydataio/io/utils/class_helper.py
pydataio/io/utils/duration.py
pydataio/io/utils/triggers.py
pydataio-1.1.1.dist-info/licenses/LICENSE
pydataio-1.1.1.dist-info/METADATA
pydataio-1.1.1.dist-info/WHEEL
pydataio-1.1.1.dist-info/top_level.txt
pydataio-1.1.1.dist-info/RECORD
