Metadata-Version: 2.4
Name: pydataio
Version: 1.1.1
Summary: A scalable framework for data input and output operations in Spark applications
Home-page: https://github.com/AmadeusITGroup/PyDataIO
Author: Guillaume LECLERC, Simone DE SANTIS
Author-email: Simone DE SANTIS <simone.desantis@amadeus.com>, Guillaume LECLERC <guillaume.leclerc@amadeus.com>
Requires-Python: >=3.11
License-File: LICENSE
Requires-Dist: adlfs==2024.7.0
Requires-Dist: fsspec==2024.12.0
Requires-Dist: pyyaml==6.0.3
Dynamic: license-file
